ckanext_hierarchy-1.2.0-py3.9-nspkg.pth
ckanext/hierarchy/__init__.py
ckanext/hierarchy/helpers.py
ckanext/hierarchy/model.py
ckanext/hierarchy/plugin.py
ckanext/hierarchy/fanstatic/hierarchy_theme.css
ckanext/hierarchy/fanstatic/jquery.hierarchy.js
ckanext/hierarchy/groups_hierarchy/group/about.html
ckanext/hierarchy/groups_hierarchy/group/read.html
ckanext/hierarchy/groups_hierarchy/group/snippets/group_form.html
ckanext/hierarchy/groups_hierarchy/group/snippets/group_list.html
ckanext/hierarchy/groups_hierarchy/group/snippets/group_tree.html
ckanext/hierarchy/groups_hierarchy/group/snippets/info.html
ckanext/hierarchy/logic/__init__.py
ckanext/hierarchy/logic/action.py
ckanext/hierarchy/templates/hierarchy/snippets/hierarchy_asset.html
ckanext/hierarchy/templates/hierarchy/snippets/hierarchy_resource.html
ckanext/hierarchy/templates/organization/about.html
ckanext/hierarchy/templates/organization/read.html
ckanext/hierarchy/templates/organization/snippets/organization_form.html
ckanext/hierarchy/templates/organization/snippets/organization_list.html
ckanext/hierarchy/templates/organization/snippets/organization_tree.html
ckanext/hierarchy/templates/package/base.html
ckanext/hierarchy/templates/scheming/form_snippets/hierarchy_image_url.html
ckanext/hierarchy/templates/scheming/form_snippets/org_hierarchy.html
ckanext/hierarchy/templates/scheming/organization/about.html
ckanext/hierarchy/templates/snippets/organization.html
ckanext/hierarchy/templates/snippets/search_form.html
ckanext/hierarchy/tests/__init__.py
ckanext/hierarchy/tests/fixtures.py
ckanext/hierarchy/tests/test_plugin.py
ckanext/hierarchy/tests/test_unaffected.py
ckanext_hierarchy-1.2.0.dist-info/LICENSE
ckanext_hierarchy-1.2.0.dist-info/METADATA
ckanext_hierarchy-1.2.0.dist-info/WHEEL
ckanext_hierarchy-1.2.0.dist-info/entry_points.txt
ckanext_hierarchy-1.2.0.dist-info/namespace_packages.txt
ckanext_hierarchy-1.2.0.dist-info/top_level.txt
ckanext_hierarchy-1.2.0.dist-info/RECORD
