Metadata-Version: 2.1
Name: ckanext-hierarchy
Version: 1.2.0
Summary: CKAN Organization hierarchy - templates and configuration
Home-page: https://github.com/davidread/ckanext-hierarchy
Author: David Read
Author-email: david.read@hackneyworkshop.com
License: AGPL
Keywords: CKAN
Classifier: Development Status :: 4 - Beta
Classifier: License :: OSI Approved :: GNU Affero General Public License v3 or later (AGPLv3+)
Classifier: Programming Language :: Python :: 2.7
License-File: LICENSE
